[
  {
    "verse": 1,
    "start": 0.0,
    "end": 15.1
  },
  {
    "verse": 2,
    "start": 14.36,
    "end": 28.56
  },
  {
    "verse": 3,
    "start": 28.12,
    "end": 42.84
  },
  {
    "verse": 4,
    "start": 42.18,
    "end": 55.72
  },
  {
    "verse": 5,
    "start": 54.94,
    "end": 70.28
  },
  {
    "verse": 6,
    "start": 70.0,
    "end": 86.76
  },
  {
    "verse": 7,
    "start": 86.44,
    "end": 103.14
  },
  {
    "verse": 8,
    "start": 102.68,
    "end": 115.48
  },
  {
    "verse": 9,
    "start": 114.9,
    "end": 126.1
  },
  {
    "verse": 10,
    "start": 125.6,
    "end": 137.88
  },
  {
    "verse": 11,
    "start": 137.44,
    "end": 153.02
  },
  {
    "verse": 12,
    "start": 152.68,
    "end": 168.46
  },
  {
    "verse": 13,
    "start": 168.2,
    "end": 181.5
  },
  {
    "verse": 14,
    "start": 181.18,
    "end": 199.36
  },
  {
    "verse": 15,
    "start": 199.12,
    "end": 208.64
  },
  {
    "verse": 16,
    "start": 208.36,
    "end": 219.6
  },
  {
    "verse": 17,
    "start": 219.42,
    "end": 244.2
  },
  {
    "verse": 18,
    "start": 243.86,
    "end": 257.66
  },
  {
    "verse": 19,
    "start": 257.58,
    "end": 275.12
  },
  {
    "verse": 20,
    "start": 274.7,
    "end": 283.92
  },
  {
    "verse": 21,
    "start": 283.52,
    "end": 300.7
  },
  {
    "verse": 22,
    "start": 300.34,
    "end": 307.26
  },
  {
    "verse": 23,
    "start": 306.84,
    "end": 325.26
  },
  {
    "verse": 24,
    "start": 324.84,
    "end": 332.7
  },
  {
    "verse": 25,
    "start": 332.54,
    "end": 352.12
  }
]