[
  {
    "verse": 1,
    "start": 1.28,
    "end": 24.54
  },
  {
    "verse": 2,
    "start": 23.88,
    "end": 36.34
  },
  {
    "verse": 3,
    "start": 35.84,
    "end": 49.88
  },
  {
    "verse": 4,
    "start": 49.46,
    "end": 58.76
  },
  {
    "verse": 5,
    "start": 58.44,
    "end": 70.56
  },
  {
    "verse": 6,
    "start": 70.4,
    "end": 78.92
  },
  {
    "verse": 7,
    "start": 78.74,
    "end": 90.52
  },
  {
    "verse": 8,
    "start": 90.18,
    "end": 98.2
  },
  {
    "verse": 9,
    "start": 98.04,
    "end": 109.68
  },
  {
    "verse": 10,
    "start": 109.3,
    "end": 128.06
  },
  {
    "verse": 11,
    "start": 127.36,
    "end": 145.78
  },
  {
    "verse": 12,
    "start": 145.24,
    "end": 160.18
  },
  {
    "verse": 13,
    "start": 159.58,
    "end": 171.3
  },
  {
    "verse": 14,
    "start": 170.76,
    "end": 185.7
  },
  {
    "verse": 15,
    "start": 185.24,
    "end": 193.18
  },
  {
    "verse": 16,
    "start": 192.84,
    "end": 208.4
  },
  {
    "verse": 17,
    "start": 208.08,
    "end": 215.54
  },
  {
    "verse": 18,
    "start": 215.06,
    "end": 231.38
  },
  {
    "verse": 19,
    "start": 231.04,
    "end": 247.48
  },
  {
    "verse": 20,
    "start": 247.24,
    "end": 257.6
  },
  {
    "verse": 21,
    "start": 257.26,
    "end": 267.9
  },
  {
    "verse": 22,
    "start": 267.54,
    "end": 281.02
  },
  {
    "verse": 23,
    "start": 280.66,
    "end": 296.28
  },
  {
    "verse": 24,
    "start": 296.0,
    "end": 307.4
  }
]