[
  {
    "verse": 1,
    "start": 0.94,
    "end": 6.82
  },
  {
    "verse": 2,
    "start": 6.08,
    "end": 14.38
  },
  {
    "verse": 3,
    "start": 14.24,
    "end": 24.16
  },
  {
    "verse": 4,
    "start": 23.32,
    "end": 31.06
  },
  {
    "verse": 5,
    "start": 30.78,
    "end": 42.3
  },
  {
    "verse": 6,
    "start": 42.06,
    "end": 47.84
  },
  {
    "verse": 7,
    "start": 47.58,
    "end": 56.5
  },
  {
    "verse": 8,
    "start": 56.28,
    "end": 67.52
  },
  {
    "verse": 9,
    "start": 67.22,
    "end": 75.02
  },
  {
    "verse": 10,
    "start": 74.06,
    "end": 85.44
  },
  {
    "verse": 11,
    "start": 84.76,
    "end": 90.46
  },
  {
    "verse": 12,
    "start": 89.94,
    "end": 102.44
  },
  {
    "verse": 13,
    "start": 101.96,
    "end": 110.64
  },
  {
    "verse": 14,
    "start": 109.9,
    "end": 123.44
  },
  {
    "verse": 15,
    "start": 123.06,
    "end": 132.88
  }
]