[
  {
    "verse": 1,
    "start": 0.0,
    "end": 27.94
  },
  {
    "verse": 2,
    "start": 27.54,
    "end": 42.06
  },
  {
    "verse": 3,
    "start": 41.58,
    "end": 58.26
  },
  {
    "verse": 4,
    "start": 57.84,
    "end": 61.64
  },
  {
    "verse": 5,
    "start": 61.34,
    "end": 78.72
  },
  {
    "verse": 6,
    "start": 78.36,
    "end": 94.98
  },
  {
    "verse": 7,
    "start": 94.64,
    "end": 109.38
  },
  {
    "verse": 8,
    "start": 109.04,
    "end": 133.0
  },
  {
    "verse": 9,
    "start": 132.72,
    "end": 151.58
  },
  {
    "verse": 10,
    "start": 151.14,
    "end": 164.12
  }
]