[
  {
    "verse": 1,
    "start": 0.0,
    "end": 10.64
  },
  {
    "verse": 2,
    "start": 10.36,
    "end": 20.54
  },
  {
    "verse": 3,
    "start": 20.0,
    "end": 33.22
  },
  {
    "verse": 4,
    "start": 32.54,
    "end": 40.22
  },
  {
    "verse": 5,
    "start": 39.78,
    "end": 50.18
  },
  {
    "verse": 6,
    "start": 49.58,
    "end": 58.24
  },
  {
    "verse": 7,
    "start": 57.82,
    "end": 64.66
  },
  {
    "verse": 8,
    "start": 64.4,
    "end": 83.06
  },
  {
    "verse": 9,
    "start": 82.86,
    "end": 88.72
  },
  {
    "verse": 10,
    "start": 88.4,
    "end": 93.7
  },
  {
    "verse": 11,
    "start": 93.18,
    "end": 102.82
  },
  {
    "verse": 12,
    "start": 102.58,
    "end": 105.88
  },
  {
    "verse": 13,
    "start": 105.6,
    "end": 115.98
  },
  {
    "verse": 14,
    "start": 115.14,
    "end": 125.0
  },
  {
    "verse": 15,
    "start": 124.7,
    "end": 131.28
  },
  {
    "verse": 16,
    "start": 130.48,
    "end": 139.8
  },
  {
    "verse": 17,
    "start": 139.52,
    "end": 153.34
  },
  {
    "verse": 18,
    "start": 152.9,
    "end": 165.44
  },
  {
    "verse": 19,
    "start": 165.04,
    "end": 171.12
  },
  {
    "verse": 20,
    "start": 170.58,
    "end": 177.6
  },
  {
    "verse": 21,
    "start": 176.96,
    "end": 186.4
  },
  {
    "verse": 22,
    "start": 186.18,
    "end": 193.06
  }
]