[
  {
    "verse": 1,
    "start": 0.84,
    "end": 8.6
  },
  {
    "verse": 2,
    "start": 7.78,
    "end": 22.32
  },
  {
    "verse": 3,
    "start": 22.08,
    "end": 39.88
  },
  {
    "verse": 4,
    "start": 39.38,
    "end": 46.46
  },
  {
    "verse": 5,
    "start": 46.28,
    "end": 81.18
  },
  {
    "verse": 6,
    "start": 80.88,
    "end": 93.26
  },
  {
    "verse": 7,
    "start": 93.04,
    "end": 107.2
  },
  {
    "verse": 8,
    "start": 106.78,
    "end": 123.56
  },
  {
    "verse": 9,
    "start": 123.32,
    "end": 142.1
  },
  {
    "verse": 10,
    "start": 141.6,
    "end": 154.22
  },
  {
    "verse": 11,
    "start": 153.76,
    "end": 164.42
  },
  {
    "verse": 12,
    "start": 164.22,
    "end": 185.66
  },
  {
    "verse": 13,
    "start": 185.16,
    "end": 196.24
  },
  {
    "verse": 14,
    "start": 195.96,
    "end": 212.0
  },
  {
    "verse": 15,
    "start": 211.84,
    "end": 233.54
  },
  {
    "verse": 16,
    "start": 233.22,
    "end": 241.48
  },
  {
    "verse": 17,
    "start": 241.2,
    "end": 257.62
  },
  {
    "verse": 18,
    "start": 257.46,
    "end": 282.06
  },
  {
    "verse": 19,
    "start": 281.6,
    "end": 302.62
  },
  {
    "verse": 20,
    "start": 302.3,
    "end": 314.88
  },
  {
    "verse": 21,
    "start": 314.5,
    "end": 328.66
  }
]