[
  {
    "verse": 1,
    "start": 1.52,
    "end": 18.78
  },
  {
    "verse": 2,
    "start": 18.22,
    "end": 35.38
  },
  {
    "verse": 3,
    "start": 35.0,
    "end": 52.0
  },
  {
    "verse": 4,
    "start": 51.04,
    "end": 65.8
  },
  {
    "verse": 5,
    "start": 65.52,
    "end": 79.68
  },
  {
    "verse": 6,
    "start": 79.22,
    "end": 96.34
  },
  {
    "verse": 7,
    "start": 96.0,
    "end": 113.1
  },
  {
    "verse": 8,
    "start": 112.84,
    "end": 127.58
  },
  {
    "verse": 9,
    "start": 126.94,
    "end": 143.32
  },
  {
    "verse": 10,
    "start": 142.98,
    "end": 152.42
  },
  {
    "verse": 11,
    "start": 151.96,
    "end": 163.42
  },
  {
    "verse": 12,
    "start": 163.18,
    "end": 177.7
  },
  {
    "verse": 13,
    "start": 177.44,
    "end": 199.64
  },
  {
    "verse": 14,
    "start": 199.26,
    "end": 211.56
  },
  {
    "verse": 15,
    "start": 211.2,
    "end": 218.9
  },
  {
    "verse": 16,
    "start": 218.42,
    "end": 242.26
  },
  {
    "verse": 17,
    "start": 242.06,
    "end": 253.42
  },
  {
    "verse": 18,
    "start": 252.94,
    "end": 263.48
  },
  {
    "verse": 19,
    "start": 263.08,
    "end": 278.72
  },
  {
    "verse": 20,
    "start": 278.48,
    "end": 296.82
  },
  {
    "verse": 21,
    "start": 296.36,
    "end": 313.1
  },
  {
    "verse": 22,
    "start": 312.7,
    "end": 325.16
  },
  {
    "verse": 23,
    "start": 324.86,
    "end": 333.02
  },
  {
    "verse": 24,
    "start": 332.56,
    "end": 352.32
  },
  {
    "verse": 25,
    "start": 352.14,
    "end": 365.04
  },
  {
    "verse": 26,
    "start": 364.94,
    "end": 384.38
  },
  {
    "verse": 27,
    "start": 384.06,
    "end": 397.9
  }
]