[
  {
    "verse": 1,
    "start": 0.0,
    "end": 6.32
  },
  {
    "verse": 2,
    "start": 5.92,
    "end": 19.76
  },
  {
    "verse": 3,
    "start": 19.44,
    "end": 29.82
  },
  {
    "verse": 4,
    "start": 29.5,
    "end": 42.94
  },
  {
    "verse": 5,
    "start": 42.64,
    "end": 57.56
  },
  {
    "verse": 6,
    "start": 57.32,
    "end": 70.36
  },
  {
    "verse": 7,
    "start": 69.86,
    "end": 81.66
  },
  {
    "verse": 8,
    "start": 81.44,
    "end": 94.3
  },
  {
    "verse": 9,
    "start": 93.92,
    "end": 102.66
  },
  {
    "verse": 10,
    "start": 102.3,
    "end": 117.66
  },
  {
    "verse": 11,
    "start": 117.28,
    "end": 127.06
  },
  {
    "verse": 12,
    "start": 126.6,
    "end": 133.28
  },
  {
    "verse": 13,
    "start": 132.78,
    "end": 141.4
  },
  {
    "verse": 14,
    "start": 141.12,
    "end": 149.32
  },
  {
    "verse": 15,
    "start": 148.86,
    "end": 156.04
  },
  {
    "verse": 16,
    "start": 155.88,
    "end": 167.58
  },
  {
    "verse": 17,
    "start": 167.28,
    "end": 177.92
  },
  {
    "verse": 18,
    "start": 177.2,
    "end": 182.7
  },
  {
    "verse": 19,
    "start": 182.44,
    "end": 195.36
  },
  {
    "verse": 20,
    "start": 195.08,
    "end": 205.5
  },
  {
    "verse": 21,
    "start": 205.26,
    "end": 213.06
  },
  {
    "verse": 22,
    "start": 212.84,
    "end": 222.94
  },
  {
    "verse": 23,
    "start": 222.7,
    "end": 231.56
  },
  {
    "verse": 24,
    "start": 231.2,
    "end": 241.86
  },
  {
    "verse": 25,
    "start": 241.46,
    "end": 250.32
  },
  {
    "verse": 26,
    "start": 249.66,
    "end": 263.42
  },
  {
    "verse": 27,
    "start": 263.1,
    "end": 272.9
  },
  {
    "verse": 28,
    "start": 272.58,
    "end": 279.08
  },
  {
    "verse": 29,
    "start": 278.5,
    "end": 287.74
  },
  {
    "verse": 30,
    "start": 287.36,
    "end": 299.22
  },
  {
    "verse": 31,
    "start": 298.86,
    "end": 309.44
  },
  {
    "verse": 32,
    "start": 308.88,
    "end": 321.14
  },
  {
    "verse": 33,
    "start": 320.82,
    "end": 330.66
  },
  {
    "verse": 34,
    "start": 330.48,
    "end": 345.88
  },
  {
    "verse": 35,
    "start": 345.42,
    "end": 361.7
  },
  {
    "verse": 36,
    "start": 361.3,
    "end": 370.72
  },
  {
    "verse": 37,
    "start": 370.28,
    "end": 384.62
  },
  {
    "verse": 38,
    "start": 384.16,
    "end": 397.3
  },
  {
    "verse": 39,
    "start": 397.14,
    "end": 406.24
  },
  {
    "verse": 40,
    "start": 405.8,
    "end": 419.38
  },
  {
    "verse": 41,
    "start": 419.02,
    "end": 429.16
  },
  {
    "verse": 42,
    "start": 428.96,
    "end": 445.3
  },
  {
    "verse": 43,
    "start": 444.92,
    "end": 458.76
  },
  {
    "verse": 44,
    "start": 458.4,
    "end": 473.78
  },
  {
    "verse": 45,
    "start": 473.32,
    "end": 487.66
  },
  {
    "verse": 46,
    "start": 487.32,
    "end": 495.22
  },
  {
    "verse": 47,
    "start": 494.9,
    "end": 498.6
  },
  {
    "verse": 48,
    "start": 498.3,
    "end": 505.3
  },
  {
    "verse": 49,
    "start": 505.04,
    "end": 517.74
  },
  {
    "verse": 50,
    "start": 517.48,
    "end": 522.06
  },
  {
    "verse": 51,
    "start": 521.66,
    "end": 533.76
  },
  {
    "verse": 52,
    "start": 533.44,
    "end": 548.38
  },
  {
    "verse": 53,
    "start": 547.46,
    "end": 555.44
  },
  {
    "verse": 54,
    "start": 555.14,
    "end": 562.82
  },
  {
    "verse": 55,
    "start": 562.5,
    "end": 583.14
  },
  {
    "verse": 56,
    "start": 582.74,
    "end": 592.36
  },
  {
    "verse": 57,
    "start": 591.6,
    "end": 604.52
  },
  {
    "verse": 58,
    "start": 604.06,
    "end": 611.68
  },
  {
    "verse": 59,
    "start": 610.96,
    "end": 630.92
  }
]