[
  {
    "verse": 1,
    "start": 0.0,
    "end": 20.12
  },
  {
    "verse": 2,
    "start": 19.94,
    "end": 34.02
  },
  {
    "verse": 3,
    "start": 33.24,
    "end": 50.96
  },
  {
    "verse": 4,
    "start": 50.6,
    "end": 72.76
  },
  {
    "verse": 5,
    "start": 72.62,
    "end": 89.74
  },
  {
    "verse": 6,
    "start": 89.22,
    "end": 104.6
  },
  {
    "verse": 7,
    "start": 103.92,
    "end": 114.58
  },
  {
    "verse": 8,
    "start": 114.32,
    "end": 120.56
  },
  {
    "verse": 9,
    "start": 120.36,
    "end": 131.2
  },
  {
    "verse": 10,
    "start": 130.82,
    "end": 146.04
  },
  {
    "verse": 11,
    "start": 145.76,
    "end": 154.86
  },
  {
    "verse": 12,
    "start": 154.5,
    "end": 168.7
  },
  {
    "verse": 13,
    "start": 168.42,
    "end": 180.52
  },
  {
    "verse": 14,
    "start": 180.06,
    "end": 190.46
  },
  {
    "verse": 15,
    "start": 190.16,
    "end": 198.08
  },
  {
    "verse": 16,
    "start": 197.96,
    "end": 218.62
  },
  {
    "verse": 17,
    "start": 218.08,
    "end": 232.7
  },
  {
    "verse": 18,
    "start": 231.78,
    "end": 240.52
  },
  {
    "verse": 19,
    "start": 240.16,
    "end": 252.24
  },
  {
    "verse": 20,
    "start": 251.74,
    "end": 259.94
  },
  {
    "verse": 21,
    "start": 259.4,
    "end": 277.98
  },
  {
    "verse": 22,
    "start": 277.54,
    "end": 293.58
  },
  {
    "verse": 23,
    "start": 293.42,
    "end": 305.44
  },
  {
    "verse": 24,
    "start": 304.96,
    "end": 320.76
  },
  {
    "verse": 25,
    "start": 320.42,
    "end": 332.54
  },
  {
    "verse": 26,
    "start": 332.34,
    "end": 348.24
  },
  {
    "verse": 27,
    "start": 347.96,
    "end": 358.58
  },
  {
    "verse": 28,
    "start": 358.04,
    "end": 368.58
  },
  {
    "verse": 29,
    "start": 368.3,
    "end": 387.52
  },
  {
    "verse": 30,
    "start": 387.08,
    "end": 394.58
  },
  {
    "verse": 31,
    "start": 394.02,
    "end": 406.74
  },
  {
    "verse": 32,
    "start": 406.24,
    "end": 414.68
  },
  {
    "verse": 33,
    "start": 414.42,
    "end": 432.2
  },
  {
    "verse": 34,
    "start": 431.54,
    "end": 448.7
  },
  {
    "verse": 35,
    "start": 448.42,
    "end": 457.8
  },
  {
    "verse": 36,
    "start": 457.42,
    "end": 471.38
  },
  {
    "verse": 37,
    "start": 470.62,
    "end": 487.86
  },
  {
    "verse": 38,
    "start": 487.56,
    "end": 494.78
  },
  {
    "verse": 39,
    "start": 494.62,
    "end": 510.4
  },
  {
    "verse": 40,
    "start": 510.12,
    "end": 526.1
  },
  {
    "verse": 41,
    "start": 525.82,
    "end": 538.34
  },
  {
    "verse": 42,
    "start": 537.72,
    "end": 558.78
  },
  {
    "verse": 43,
    "start": 558.46,
    "end": 569.48
  },
  {
    "verse": 44,
    "start": 569.26,
    "end": 588.34
  },
  {
    "verse": 45,
    "start": 588.24,
    "end": 599.12
  },
  {
    "verse": 46,
    "start": 598.56,
    "end": 615.48
  },
  {
    "verse": 47,
    "start": 615.1,
    "end": 627.18
  },
  {
    "verse": 48,
    "start": 626.7,
    "end": 644.28
  },
  {
    "verse": 49,
    "start": 644.14,
    "end": 660.69
  }
]