[
  {
    "verse": 1,
    "start": 1.4,
    "end": 8.3
  },
  {
    "verse": 2,
    "start": 7.52,
    "end": 21.4
  },
  {
    "verse": 3,
    "start": 21.26,
    "end": 31.6
  },
  {
    "verse": 4,
    "start": 31.36,
    "end": 44.32
  },
  {
    "verse": 5,
    "start": 44.08,
    "end": 57.84
  },
  {
    "verse": 6,
    "start": 57.3,
    "end": 69.68
  },
  {
    "verse": 7,
    "start": 69.1,
    "end": 75.9
  },
  {
    "verse": 8,
    "start": 75.42,
    "end": 87.2
  },
  {
    "verse": 9,
    "start": 87.04,
    "end": 97.86
  },
  {
    "verse": 10,
    "start": 97.72,
    "end": 118.52
  },
  {
    "verse": 11,
    "start": 118.28,
    "end": 133.06
  },
  {
    "verse": 12,
    "start": 132.66,
    "end": 140.46
  },
  {
    "verse": 13,
    "start": 140.2,
    "end": 145.76
  },
  {
    "verse": 14,
    "start": 145.32,
    "end": 161.88
  },
  {
    "verse": 15,
    "start": 161.58,
    "end": 167.72
  },
  {
    "verse": 16,
    "start": 167.32,
    "end": 185.54
  },
  {
    "verse": 17,
    "start": 185.14,
    "end": 195.94
  },
  {
    "verse": 18,
    "start": 195.62,
    "end": 205.0
  },
  {
    "verse": 19,
    "start": 204.84,
    "end": 212.74
  },
  {
    "verse": 20,
    "start": 212.24,
    "end": 221.5
  },
  {
    "verse": 21,
    "start": 220.98,
    "end": 229.42
  },
  {
    "verse": 22,
    "start": 229.06,
    "end": 241.7
  },
  {
    "verse": 23,
    "start": 241.46,
    "end": 253.14
  },
  {
    "verse": 24,
    "start": 253.0,
    "end": 260.34
  },
  {
    "verse": 25,
    "start": 260.14,
    "end": 272.02
  },
  {
    "verse": 26,
    "start": 271.22,
    "end": 279.02
  },
  {
    "verse": 27,
    "start": 278.7,
    "end": 292.08
  },
  {
    "verse": 28,
    "start": 291.56,
    "end": 311.16
  },
  {
    "verse": 29,
    "start": 310.82,
    "end": 321.62
  },
  {
    "verse": 30,
    "start": 321.16,
    "end": 336.48
  },
  {
    "verse": 31,
    "start": 336.12,
    "end": 352.74
  },
  {
    "verse": 32,
    "start": 352.38,
    "end": 358.64
  },
  {
    "verse": 33,
    "start": 358.0,
    "end": 373.18
  },
  {
    "verse": 34,
    "start": 372.78,
    "end": 380.0
  },
  {
    "verse": 35,
    "start": 379.86,
    "end": 391.38
  },
  {
    "verse": 36,
    "start": 391.1,
    "end": 401.08
  },
  {
    "verse": 37,
    "start": 400.78,
    "end": 409.36
  },
  {
    "verse": 38,
    "start": 408.7,
    "end": 421.4
  },
  {
    "verse": 39,
    "start": 421.02,
    "end": 431.96
  },
  {
    "verse": 40,
    "start": 431.5,
    "end": 440.98
  },
  {
    "verse": 41,
    "start": 440.66,
    "end": 451.0
  },
  {
    "verse": 42,
    "start": 450.62,
    "end": 459.96
  },
  {
    "verse": 43,
    "start": 459.6,
    "end": 465.64
  },
  {
    "verse": 44,
    "start": 465.38,
    "end": 473.32
  },
  {
    "verse": 45,
    "start": 472.86,
    "end": 483.76
  },
  {
    "verse": 46,
    "start": 483.18,
    "end": 497.1
  },
  {
    "verse": 47,
    "start": 496.84,
    "end": 511.38
  },
  {
    "verse": 48,
    "start": 511.06,
    "end": 518.3
  },
  {
    "verse": 49,
    "start": 517.84,
    "end": 531.52
  },
  {
    "verse": 50,
    "start": 531.42,
    "end": 547.9
  },
  {
    "verse": 51,
    "start": 547.3,
    "end": 556.0
  },
  {
    "verse": 52,
    "start": 555.4,
    "end": 569.1
  },
  {
    "verse": 53,
    "start": 568.1,
    "end": 577.66
  },
  {
    "verse": 54,
    "start": 576.84,
    "end": 587.06
  },
  {
    "verse": 55,
    "start": 586.66,
    "end": 595.54
  }
]