[
  {
    "verse": 1,
    "start": 0.0,
    "end": 17.18
  },
  {
    "verse": 2,
    "start": 16.32,
    "end": 25.88
  },
  {
    "verse": 3,
    "start": 25.6,
    "end": 36.76
  },
  {
    "verse": 4,
    "start": 36.42,
    "end": 45.5
  },
  {
    "verse": 5,
    "start": 45.0,
    "end": 52.24
  },
  {
    "verse": 6,
    "start": 52.02,
    "end": 61.36
  },
  {
    "verse": 7,
    "start": 61.1,
    "end": 67.28
  },
  {
    "verse": 8,
    "start": 66.9,
    "end": 77.14
  },
  {
    "verse": 9,
    "start": 76.78,
    "end": 83.62
  },
  {
    "verse": 10,
    "start": 83.26,
    "end": 88.22
  },
  {
    "verse": 11,
    "start": 87.86,
    "end": 97.2
  },
  {
    "verse": 12,
    "start": 96.94,
    "end": 104.22
  },
  {
    "verse": 13,
    "start": 103.74,
    "end": 113.94
  },
  {
    "verse": 14,
    "start": 113.66,
    "end": 132.44
  },
  {
    "verse": 15,
    "start": 132.26,
    "end": 143.28
  }
]