[
  {
    "verse": 1,
    "start": 0.0,
    "end": 16.0
  },
  {
    "verse": 2,
    "start": 15.48,
    "end": 30.92
  },
  {
    "verse": 3,
    "start": 30.6,
    "end": 50.02
  },
  {
    "verse": 4,
    "start": 49.44,
    "end": 73.1
  },
  {
    "verse": 5,
    "start": 72.58,
    "end": 81.44
  },
  {
    "verse": 6,
    "start": 81.28,
    "end": 89.76
  },
  {
    "verse": 7,
    "start": 89.44,
    "end": 102.68
  },
  {
    "verse": 8,
    "start": 102.06,
    "end": 117.24
  },
  {
    "verse": 9,
    "start": 116.86,
    "end": 129.08
  },
  {
    "verse": 10,
    "start": 128.58,
    "end": 141.58
  },
  {
    "verse": 11,
    "start": 141.42,
    "end": 159.32
  },
  {
    "verse": 12,
    "start": 158.82,
    "end": 180.3
  },
  {
    "verse": 13,
    "start": 179.6,
    "end": 196.86
  }
]