[
  {
    "verse": 1,
    "start": 0.0,
    "end": 17.48
  },
  {
    "verse": 2,
    "start": 17.16,
    "end": 40.9
  },
  {
    "verse": 3,
    "start": 40.32,
    "end": 62.26
  },
  {
    "verse": 4,
    "start": 61.46,
    "end": 75.84
  },
  {
    "verse": 5,
    "start": 75.18,
    "end": 89.54
  },
  {
    "verse": 6,
    "start": 89.18,
    "end": 102.2
  },
  {
    "verse": 7,
    "start": 101.98,
    "end": 118.94
  },
  {
    "verse": 8,
    "start": 118.56,
    "end": 134.02
  },
  {
    "verse": 9,
    "start": 133.86,
    "end": 148.84
  },
  {
    "verse": 10,
    "start": 148.54,
    "end": 174.52
  },
  {
    "verse": 11,
    "start": 174.14,
    "end": 185.82
  },
  {
    "verse": 12,
    "start": 185.48,
    "end": 198.86
  },
  {
    "verse": 13,
    "start": 198.46,
    "end": 221.4
  }
]