[
  {
    "verse": 1,
    "start": 0.0,
    "end": 9.66
  },
  {
    "verse": 2,
    "start": 9.46,
    "end": 23.4
  },
  {
    "verse": 3,
    "start": 23.02,
    "end": 33.44
  },
  {
    "verse": 4,
    "start": 33.28,
    "end": 42.4
  },
  {
    "verse": 5,
    "start": 41.8,
    "end": 51.16
  },
  {
    "verse": 6,
    "start": 50.7,
    "end": 59.82
  },
  {
    "verse": 7,
    "start": 59.18,
    "end": 67.94
  },
  {
    "verse": 8,
    "start": 67.1,
    "end": 79.5
  },
  {
    "verse": 9,
    "start": 78.92,
    "end": 87.58
  },
  {
    "verse": 10,
    "start": 87.12,
    "end": 102.28
  },
  {
    "verse": 11,
    "start": 101.86,
    "end": 110.26
  },
  {
    "verse": 12,
    "start": 110.12,
    "end": 122.18
  },
  {
    "verse": 13,
    "start": 121.36,
    "end": 129.04
  },
  {
    "verse": 14,
    "start": 128.66,
    "end": 135.1
  },
  {
    "verse": 15,
    "start": 134.5,
    "end": 150.58
  },
  {
    "verse": 16,
    "start": 150.12,
    "end": 158.16
  },
  {
    "verse": 17,
    "start": 157.84,
    "end": 166.96
  },
  {
    "verse": 18,
    "start": 166.58,
    "end": 175.1
  },
  {
    "verse": 19,
    "start": 174.86,
    "end": 183.7
  },
  {
    "verse": 20,
    "start": 183.32,
    "end": 193.94
  },
  {
    "verse": 21,
    "start": 193.52,
    "end": 204.42
  },
  {
    "verse": 22,
    "start": 203.92,
    "end": 210.96
  },
  {
    "verse": 23,
    "start": 210.6,
    "end": 223.0
  },
  {
    "verse": 24,
    "start": 222.48,
    "end": 231.44
  },
  {
    "verse": 25,
    "start": 231.2,
    "end": 239.2
  },
  {
    "verse": 26,
    "start": 238.44,
    "end": 247.94
  },
  {
    "verse": 27,
    "start": 247.68,
    "end": 257.92
  },
  {
    "verse": 28,
    "start": 257.68,
    "end": 275.08
  },
  {
    "verse": 29,
    "start": 274.46,
    "end": 281.64
  },
  {
    "verse": 30,
    "start": 281.26,
    "end": 291.42
  },
  {
    "verse": 31,
    "start": 290.98,
    "end": 298.94
  },
  {
    "verse": 32,
    "start": 298.38,
    "end": 309.1
  },
  {
    "verse": 33,
    "start": 308.76,
    "end": 317.88
  },
  {
    "verse": 34,
    "start": 317.54,
    "end": 328.88
  }
]