[
  {
    "verse": 1,
    "start": 0.94,
    "end": 12.24
  },
  {
    "verse": 2,
    "start": 11.92,
    "end": 24.38
  },
  {
    "verse": 3,
    "start": 24.12,
    "end": 36.92
  },
  {
    "verse": 4,
    "start": 36.36,
    "end": 43.24
  },
  {
    "verse": 5,
    "start": 43.02,
    "end": 50.22
  },
  {
    "verse": 6,
    "start": 49.72,
    "end": 62.94
  },
  {
    "verse": 7,
    "start": 62.46,
    "end": 76.1
  },
  {
    "verse": 8,
    "start": 75.62,
    "end": 84.7
  },
  {
    "verse": 9,
    "start": 84.2,
    "end": 92.08
  },
  {
    "verse": 10,
    "start": 91.66,
    "end": 105.1
  },
  {
    "verse": 11,
    "start": 104.6,
    "end": 118.64
  },
  {
    "verse": 12,
    "start": 118.2,
    "end": 128.28
  },
  {
    "verse": 13,
    "start": 127.86,
    "end": 137.08
  },
  {
    "verse": 14,
    "start": 136.64,
    "end": 145.84
  },
  {
    "verse": 15,
    "start": 145.22,
    "end": 154.86
  },
  {
    "verse": 16,
    "start": 154.44,
    "end": 162.98
  },
  {
    "verse": 17,
    "start": 162.28,
    "end": 171.44
  },
  {
    "verse": 18,
    "start": 170.92,
    "end": 178.42
  },
  {
    "verse": 19,
    "start": 177.92,
    "end": 194.42
  },
  {
    "verse": 20,
    "start": 193.66,
    "end": 203.2
  },
  {
    "verse": 21,
    "start": 202.7,
    "end": 210.9
  },
  {
    "verse": 22,
    "start": 210.0,
    "end": 220.84
  },
  {
    "verse": 23,
    "start": 220.6,
    "end": 229.14
  },
  {
    "verse": 24,
    "start": 228.88,
    "end": 238.92
  },
  {
    "verse": 25,
    "start": 238.54,
    "end": 247.52
  },
  {
    "verse": 26,
    "start": 247.02,
    "end": 259.32
  },
  {
    "verse": 27,
    "start": 259.02,
    "end": 272.64
  },
  {
    "verse": 28,
    "start": 272.4,
    "end": 290.04
  },
  {
    "verse": 29,
    "start": 289.8,
    "end": 302.04
  },
  {
    "verse": 30,
    "start": 301.68,
    "end": 313.02
  },
  {
    "verse": 31,
    "start": 312.82,
    "end": 320.58
  },
  {
    "verse": 32,
    "start": 320.26,
    "end": 327.98
  },
  {
    "verse": 33,
    "start": 327.8,
    "end": 345.22
  },
  {
    "verse": 34,
    "start": 344.92,
    "end": 352.44
  },
  {
    "verse": 35,
    "start": 352.06,
    "end": 359.4
  },
  {
    "verse": 36,
    "start": 359.14,
    "end": 366.84
  },
  {
    "verse": 37,
    "start": 366.54,
    "end": 380.12
  },
  {
    "verse": 38,
    "start": 379.02,
    "end": 386.46
  }
]